<?xml version='1.0' encoding='UTF-8'?>
<song xmlns="http://openlyrics.info/namespace/2009/song" version="0.8" createdIn="OpenLP 2.4.6" modifiedIn="OpenLP 2.4.6" modifiedDate="2021-12-15T17:47:48">
  <properties>
    <titles>
      <title>Ja przyjdę wnet!</title>
    </titles>
    <authors>
      <author>Author Unknown</author>
    </authors>
    <songbooks>
      <songbook name="Pielgrzyma" entry="557"/>
    </songbooks>
  </properties>
  <lyrics>
    <verse name="v1">
      <lines>Ja przyjdę wnet! to głos Bożego Syna?<br/>Ja przyjdę wnet, więc trzymaj to, co masz!<br/>Ostatnia wnet wybije nam godzina;<br/>Czy w wierze ty i w gotowości trwasz?<br/>Przyjdź, Panie Jezu, amen, przyjdźże rychło!<br/>Przyjdź, Panie Jezu, i weź z Sobą mnie,<br/>By serce me, tęsknoty pełne, ścichło.<br/>Przyjdź, Panie Jezu, oczekuję Cię!</lines>
    </verse>
    <verse name="v2">
      <lines>Ja przyjdę wnet do Swej oblubienicy,<br/>Na ziemi wkrótce Swój osiągnę cel.<br/>Pląsajcie, wierni, drzyjcie, przeciwnicy!<br/>Czyś ty już w jasną jest ubrany biel?<br/>Przyjdź, Panie Jezu, grzechów gładzicielu,<br/>Przyjdź, Panie Jezu, w mocy Twojej krwi!<br/>Uzbrój, przygotuj jeszcze sług Twych wielu,<br/>Przyjdź, Panie Jezu, serca płoną Ci!</lines>
    </verse>
    <verse name="v3">
      <lines>Ja przyjdę wnet, oczekuj mnie w cichości,<br/>Ja przyjdę wnet, ty zawsze gotów bądź!<br/>Ja przyjdę wnet, o, wytrwaj w gotowości,<br/>Ja przyjdę wnet, by złote kłosy zżąć!<br/>Przyjdź, Panie Jezu, chętnie czekać będę,<br/>Przyjdź, Panie Jezu, ciemna noc jest tuż!<br/>Przyjdź, Panie Jezu, niechaj z Tobą siędę;<br/>Przyjdź, Panie Jezu, amen, przyjdźże już</lines>
    </verse>
  </lyrics>
</song>
