<?xml version='1.0' encoding='UTF-8'?><song xmlns="http://openlyrics.info/namespace/2009/song" version="0.8" createdIn="OpenLP 2.4.6" modifiedIn="OpenLP 2.4.6" modifiedDate="2020-02-01T12:11:13">  <properties>    <titles>      <title>A czemuż mój Jezus tak ubogo leży</title>    </titles>    <authors>      <author> </author>    </authors>  </properties>  <lyrics>	    <verse name="V1">      <lines>A czemuż mój Jezus tak ubogo leży?<br/> Ani po królewsku, ni w drogiej odzieży?<br/> Znać dlatego, by grzesznika, * Czartowskiego niewolnika,<br/> Od piekła wybawił, * Przez ubóstwo zbawił</lines>    </verse>	    <verse name="V2">      <lines>Czemuż nie w pałacach rodzi się Dziecina?<br/> Wszak świat, niebo, ziemia jego jest dziedzina?<br/> Ale w stajence ubogiej, * Na sianeczku w ten mróz srogi;<br/> W kamiennym żłóbeczku * Zimno Paniąteczku.</lines>    </verse>	    <verse name="V3">      <lines>Czemuż nie w bogatej pościeli królewskiej,<br/> Nie pod pawilonem leży Pan niebieski?<br/> Pajęczyna pawilonem, * Aby każdy był zbawionym<br/> Kochaj Go serdecznie, * Będziesz żył z Nim wiecznie.</lines>    </verse>	    <verse name="V4">      <lines>A cóż to za dworzany ma małe Dzieciątko,<br/> Syn Ojca wiecznego małe pacholątko?<br/> Osioł z wołem to dworzany, zważ człeku Pana nad pany,<br/> Bydlęta Mu służą, jak Bogu posłużą.</lines>    </verse>	    <verse name="V5">      <lines>A ty Mu tak służysz, żałość Mu zadajesz,<br/> Gdy za jego dobroć czartu się oddajesz;<br/> Porzuć twoje złe nałogi, Jezusowi łzy na nogi Wylewaj serdecznie, będziesz żył z Nim wiecznie.</lines>    </verse>	  </lyrics></song>