<?xml version='1.0' encoding='UTF-8'?><song xmlns="http://openlyrics.info/namespace/2009/song" version="0.8" createdIn="OpenLP 2.4.6" modifiedIn="OpenLP 2.4.6" modifiedDate="2020-02-01T12:11:13">  <properties>    <titles>      <title>Tryumfy Króla Niebieskiego</title>    </titles>    <authors>      <author> </author>    </authors>  </properties>  <lyrics>	    <verse name="V1">      <lines>Tryumfy Króla Niebieskiego<br/> Zstąpiły z nieba wysokiego.<br/> Pobudziły pasterzów,<br/> Dobytku swego stróżów<br/> Śpiewaniem, śpiewaniem, śpiewaniem.</lines>    </verse>	    <verse name="V2">      <lines>Chwała bądź Bogu w wysokości,<br/> A ludziom pokój na niskości.<br/> Narodził się Zbawiciel,<br/> Dusz ludzkich Odkupiciel<br/> Na ziemi, na ziemi, na ziemi.</lines>    </verse>	    <verse name="V3">      <lines>Zrodziła Maryja Dziewica<br/> Wiecznego Boga bez rodzica,<br/> By nas z piekła wybawił,<br/> A w niebieskich postawił<br/> Pałacach, pałacach, pałacach.</lines>    </verse>	    <verse name="V4">      <lines>Pasterze w podziwieniu stają,<br/> Tryumfu przyczynę badają,<br/> Co się nowego dzieje,<br/> Że tak światłość jaśnieje<br/> Nie wiedząc, nie wiedząc, nie wiedząc.</lines>    </verse>	    <verse name="V5">      <lines>Że to Bóg, gdy się dowiedzieli,<br/> Swej trzody w polu odbieżeli,<br/> Śpiesząc na powitanie<br/> Do Betlejemskiej stajni<br/> Dzieciątka, Dzieciątka, Dzieciątka.</lines>    </verse>	    <verse name="V6">      <lines>Niebieskim światłem oświeceni,<br/> Pokornie przed nim uniżeni,<br/> Bogiem Go być prawdziwym<br/> Z serca afektem żywym<br/> Wyznają, wyznają, wyznają.</lines>    </verse>	    <verse name="V7">      <lines>I które mieli z sobą dary<br/> Dzieciątku dają na ofiary:<br/> Przyjmij, o Narodzony<br/> Nas i dar przyniesiony Z ochotą, z ochotą, z ochotą.</lines>    </verse>	  </lyrics></song>